ed_archiver/__init__.py
ed_archiver/__main__.py
ed_archiver/archiver.py
ed_archiver/cli.py
ed_archiver/client.py
ed_archiver/models.py
ed_archiver/parser.py
ed_archiver/transformer.py
ed_archiver-0.1.0.dist-info/METADATA
ed_archiver-0.1.0.dist-info/WHEEL
ed_archiver-0.1.0.dist-info/entry_points.txt
ed_archiver-0.1.0.dist-info/licenses/LICENSE
ed_archiver-0.1.0.dist-info/RECORD
