Metadata-Version: 2.4
Name: ed-archiver
Version: 0.1.0
Summary: Archive Ed Discussion courses into RAG-ready JSON
License-File: LICENSE
Requires-Python: >=3.11
Requires-Dist: edapi>=0.1.0
Requires-Dist: pydantic>=2.0
Requires-Dist: rich>=13.0
